openai_streaming/__init__.py
openai_streaming/decorator.py
openai_streaming/fn_dispatcher.py
openai_streaming/stream_processing.py
openai_streaming/utils.py
openai_streaming/struct/__init__.py
openai_streaming/struct/handler.py
openai_streaming/struct/yaml_parser.py
openai_streaming-0.5.1.dist-info/LICENSE
openai_streaming-0.5.1.dist-info/METADATA
openai_streaming-0.5.1.dist-info/WHEEL
openai_streaming-0.5.1.dist-info/top_level.txt
openai_streaming-0.5.1.dist-info/RECORD
