Metadata-Version: 2.1
Name: openai-streaming
Version: 0.5.1
Summary: Work with OpenAI's streaming API at ease, with Python generators
Author-email: Almog Baku <almog.baku@gmail.com>
License: MIT
Project-URL: Homepage, https://github.com/AlmogBaku/openai-streaming
Project-URL: Bug Reports, https://github.com/AlmogBaku/openai-streaming/issues
Project-URL: Source, https://github.com/AlmogBaku/openai-streaming/
Keywords: openai,gpt,llm,streaming,stream,generator
Requires-Python: >=3.9
License-File: LICENSE
Requires-Dist: openai <2.0.0,>=1.14.0
Requires-Dist: json-streamer <0.2.0,>=0.1.0
Requires-Dist: pydantic <3.0.0,>=2.0.2
Requires-Dist: docstring-parser >=0.15
Provides-Extra: yaml
Requires-Dist: PyYAML <7.0.0,>6.0.0 ; extra == 'yaml'
